logging_spinner.py
logging_spinner-0.2.2.dist-info/DESCRIPTION.rst
logging_spinner-0.2.2.dist-info/METADATA
logging_spinner-0.2.2.dist-info/RECORD
logging_spinner-0.2.2.dist-info/WHEEL
logging_spinner-0.2.2.dist-info/metadata.json
logging_spinner-0.2.2.dist-info/top_level.txt
